LICENSE
README.md
pyproject.toml
setup.cfg
setup.py
dislash/__init__.py
dislash/application_commands/__init__.py
dislash/application_commands/_decohub.py
dislash/application_commands/context_menus_core.py
dislash/application_commands/core.py
dislash/application_commands/errors.py
dislash/application_commands/slash_client.py
dislash/application_commands/slash_core.py
dislash/application_commands/utils.py
dislash/application_commands/_modifications/__init__.py
dislash/application_commands/_modifications/new.py
dislash/application_commands/_modifications/old.py
dislash/interactions/__init__.py
dislash/interactions/app_command_interaction.py
dislash/interactions/application_command.py
dislash/interactions/interaction.py
dislash/interactions/message_components.py
dislash/interactions/message_interaction.py
dislash/interactions/types.py
disnc1.py.egg-info/PKG-INFO
disnc1.py.egg-info/SOURCES.txt
disnc1.py.egg-info/dependency_links.txt
disnc1.py.egg-info/requires.txt
disnc1.py.egg-info/top_level.txt