Metadata-Version: 2.1
Name: disnc1.py
Version: 1.7.0
Summary: nc.
Home-page: https://github.com/Lordnc/disnc/
Author: NCPD
Author-email: nc@n811nc.com
License: MIT
Project-URL: Documentation, https://amazon.com
Project-URL: Bug Reports, https://amazon.com
Project-URL: Source, https://github.com/Lordnc/disnc/
Keywords: python,discord,slash,commands,api,discord-api,discord-py,slash-commands,message-components,buttons,select-menus,context-menus
Platform: UNKNOWN
Classifier: License :: OSI Approved :: MIT License
Classifier: Intended Audience :: Developers
Classifier: Natural Language :: English
Classifier: Operating System :: OS Independent
Classifier: Programming Language :: Python :: 3.6
Classifier: Programming Language :: Python :: 3.7
Classifier: Programming Language :: Python :: 3.8
Classifier: Programming Language :: Python :: 3.9
Classifier: Topic :: Internet
Classifier: Topic :: Software Development :: Libraries
Classifier: Topic :: Software Development :: Libraries :: Python Modules
Classifier: Topic :: Utilities
Requires-Python: >=3.6, <4
License-File: LICENSE
